{
  "principal": "towney",
  "agent": "industry",
  "cycle_id": "towney-20260612-1309-688234",
  "data": {
    "score": 9,
    "industry_name": "第三代半导体/SiC衬底",
    "cycle_phase": "扩张",
    "supply_demand": "供不应求",
    "competitive_position": "龙头",
    "key_drivers": [
      "AI算力基础设施爆发：数据中心机柜功耗升至1.5MW级别，SiC成为破解电力瓶颈核心材料，预计2030年AI电源占SiC电源市场50%",
      "新能源汽车800V平台加速渗透：2026年SiC在新能源车渗透率预计达40%，单车节省电池成本400-800美元",
      "全面涨价周期启动：英飞凌2026年内两度涨价，全行业从'卷价格'转向'抢产能'，衬底厂产能利用率超90%",
      "国产替代完成全球卡位：天岳先进超越Wolfspeed成为全球出货量第一，8英寸市占率51.3%垄断地位",
      "先进封装散热新场景：台积电CoWoS若30%采用SiC中介层方案，潜在空间超10亿美元",
      "设备端订单暴增：晶升股份等碳化硅设备厂在手订单为去年同期2倍以上"
    ],
    "key_headwinds": [
      "8英寸大规模量产爬坡期，良率提升和成本控制是决定盈利能力的核心变量",
      "全球产能释放节奏若超预期可能导致价格再度承压",
      "关键设备和特种材料仍存在外部依赖风险（地缘政治）",
      "SiC当前价格较硅基IGBT仍高3-5倍，成本下降速度决定中低端渗透节奏",
      "公司2026Q1每股收益-0.1249元仍处亏损状态，盈利拐点尚需确认"
    ],
    "summary": "SiC衬底行业处于AI+新能源双引擎驱动的超级景气扩张期。2025年产能出清后供需逆转，2026年全行业进入全面涨价模式，头部厂商产能利用率超90%。天岳先进已超越Wolfspeed成为全球导电型SiC衬底出货量第一，8英寸全球市占率51.3%，客户覆盖特斯拉、博世、英飞凌等全球一线。摩根大通、摩根士丹利持续增持，外资行目标价看至106.6港元。行业整体评分9/10，核心风险为产能释放节奏和短期盈利能力。"
  }
}
