{
  "principal": "towney",
  "agent": "news",
  "cycle_id": "towney-20260629-1450-hudian",
  "data": {
    "symbol": "002463",
    "name": "沪电股份",
    "sentiment": 0.15,
    "event_impact": 5,
    "confidence": 0.7,
    "events": [
      {
        "date": "2026-06-24",
        "title": "投资者关系活动记录（华泰证券、太平资产调研）",
        "impact": "首次明确披露：约43亿元AI高端PCB扩产项目'预期2026年下半年开始试产并逐步提升产能'，产能落地时点明确；同时披露6月已完成收购昆山普江仓储100%股权（约2.07亿元）用于产能扩建。利好因素：产能释放时间表清晰、头部客户深度绑定。",
        "sentiment": 0.4,
        "event_impact": 6,
        "source": "巨潮/东方财富公告 AN202606241823814160"
      },
      {
        "date": "2026-06-22",
        "title": "第八届董事会第十九次会议决议公告 + 吸收合并全资子公司普江仓储",
        "impact": "对普江仓储进行吸收合并以优化管理架构、降低管理成本。属常规整合，对基本面影响中性偏正（运营效率提升），无重大估值冲击。",
        "sentiment": 0.1,
        "event_impact": 3,
        "source": "公告编号 2026-051"
      },
      {
        "date": "2026-06-16",
        "title": "19家机构密集调研（华宝、中信、财通、前海开源、君联资本、工银国际、新华香港等）",
        "impact": "国内外头部公私募/外资密集调研，反映机构对AI PCB赛道及公司的关注度持续高位。基调正面但管理层强调'行业入场者多、通关者少'。",
        "sentiment": 0.3,
        "event_impact": 5,
        "source": "公告 AN202606161823606360"
      },
      {
        "date": "2026-06-18",
        "title": "投资者调研（中欧基金、国海证券）",
        "impact": "重申差异化竞争战略，强调'技术优先'与产能升级式扩容。无新增重大信息，但是仓位讨论的参考时点。",
        "sentiment": 0.1,
        "event_impact": 3,
        "source": "公告 AN202606181823669664"
      },
      {
        "date": "2026-06-09",
        "title": "向香港联交所更新递交H股发行上市申请资料",
        "impact": "6月5日完成H股IPO申请材料更新，A+H双平台推进，长期有利于国际融资和品牌国际化。但短期存在A股流动性分流、稀释担忧。",
        "sentiment": 0.05,
        "event_impact": 4,
        "source": "公告编号 2026-050"
      },
      {
        "date": "2026-06-02至2026-06-10",
        "title": "高频投资者调研（6/1, 6/2, 6/5, 6/10）",
        "impact": "持续吸引机构调研，无新增基本面利空，但管理层口径维持谨慎（'结构性挤压'警示）。",
        "sentiment": 0.1,
        "event_impact": 3,
        "source": "东方财富公告列表"
      },
      {
        "date": "2026-05-27",
        "title": "股票交易异常波动公告（关键偏空信号）",
        "impact": "5/22-5/25-5/26三日累计涨幅偏离>20%触发异动。公司主动在公告中明确警示：'行业整体产能持续释放将摊薄准入门槛，未来市场竞争预计加剧，行业利润空间或将面临结构性挤压'。这是管理层罕见的'自我降温'措辞，对股价短期估值压制效应明显。是6/18清仓决策的重要伏笔之一。",
        "sentiment": -0.4,
        "event_impact": 7,
        "source": "公告编号 2026-049"
      },
      {
        "date": "2026-05-25",
        "title": "为全资子公司提供担保的进展公告",
        "impact": "常规担保事项，无重大影响。",
        "sentiment": 0,
        "event_impact": 2,
        "source": "公告"
      },
      {
        "date": "2026-05-20",
        "title": "独立董事取得独立董事资格证书 + 投资者调研",
        "impact": "高管/治理相关常规公告，无重大变动。",
        "sentiment": 0,
        "event_impact": 2,
        "source": "公告"
      }
    ],
    "post_618_changes": {
      "summary": "6/18清仓后至6/29期间，新增的事件主要是边际偏正的产能落地节点（43亿项目2026H2试产、普江仓储6月已完成收购）+ 董事会吸收合并子公司决议；未出现新增重大利空或重大利好催化。管理层口径整体仍维持'结构性挤压'警示基调，与5/27异动公告一致，未撤回。",
      "new_positive": [
        "6/24调研首次给出43亿AI高端PCB项目2026H2试产明确时间表",
        "6月完成昆山普江仓储100%股权收购（约2.07亿），产能扩张实质性推进",
        "6/22董事会通过吸收合并方案，运营效率优化"
      ],
      "new_negative": [
        "无新增显著利空事件",
        "但管理层在6/16、6/18、6/24调研中持续重复'入场者多、通关者少''利润空间结构性挤压'警示"
      ],
      "net_assessment": "6/18后基本面边际微正，但管理层情绪管理仍偏保守，没有出现可触发战略性回补的强催化"
    },
    "industry_macro": {
      "ai_server_demand": "AI推理需求持续增长，CSP资本支出加速，PCB高阶产品需求确定（管理层多次重申）",
      "competition_risk": "管理层警示行业产能扩张将摊薄准入门槛，未来竞争同质化、利润空间结构性挤压",
      "supply_chain": "高端原材料（HVLP铜箔、低损耗树脂、特种玻纤布）阶段性供应偏紧，公司战略安全库存与多元化认证应对"
    },
    "summary": "近一周（6/22-6/29）核心事件为6/24调研中明确披露43亿AI高端PCB项目2026H2试产时间表，以及6/22董事会通过吸收合并普江仓储以推进产能扩张；6/16-6/18两次机构密集调研（19家+中欧）维持基调。整体基本面边际偏正，但管理层延续5/27异动公告中'行业利润空间结构性挤压'的谨慎口径，未出现可推翻6/18清仓决策的强催化。综合情绪+0.15、事件影响5分，反映'温和正面 + 估值压制并存'的复杂局面。"
  },
  "data_quality": {
    "status": "partial",
    "primary_source": "东方财富公告API（np-anotice-stock.eastmoney.com / np-cnotice-stock.eastmoney.com）",
    "warnings": [
      "Tavily Search API 配额超限（432），web_search 通道全部不可用",
      "无法获取实时舆情热度（雪球/股吧详细帖子内容）、券商研报评级目标价变动",
      "数据全部来自公司官方公告及投资者关系记录，未补充第三方研报观点"
    ],
    "coverage": {
      "公司公告": "完整（近30天全部）",
      "机构调研": "完整（近30天全部）",
      "券商研报评级目标价": "未获取（搜索通道不可用）",
      "PCB行业政策": "通过公司投资者关系记录间接覆盖",
      "AI服务器客户动态": "通过公司投资者关系记录间接覆盖（管理层口径）",
      "舆情热度": "仅能从股吧帖子数量粗略观察（讨论热度仍较高）"
    }
  }
}