{
  "principal": "towney",
  "agent": "research",
  "cycle_id": "towney-20260629-1854-tianfu",
  "data_quality": {
    "price_source": "✅ 双源验证 (gtimg + eastmoney)",
    "price_confidence": "high",
    "kline_source": "腾讯gtimg qfq复权 121日",
    "valuation_source": "gtimg实时PE + 同花顺财务摘要",
    "web_search": "❌ DuckDuckGo bot-detection，Bing bot-detection，新浪研报空返。机构研报数据不可用，已在各维度标注。",
    "notes": "PE分位数为基于2年价格区间+EPS变化的估计值（数据源不可直接获取历史PE序列），PB/PS分位数缺失"
  },
  "data": {
    "symbol": "300394",
    "name": "天孚通信",
    "dimensions": {
      "technical": {
        "score": 3,
        "note": "短期严重偏空。今日-7.19%为板块最大跌幅（中际-2.70%/新易盛-1.60%），放量跌破MA5(318.29)/MA10(321.33)/MA20(317.81)三道短期均线。MACD死叉(DIF 9.55 < DEA 12.77)且绿柱扩大。RSI(6)=29.9逼近超卖但无背离确认。KDJ K=50.5跌破D=61.0呈死叉。ATR(14)=24.59(8.33%)极高波动——日均振幅约±25元。布林带宽度23.50%极端扩张，价格仅位于带内19.7%低位。OBV 5日-2.97%资金持续流出。10日回撤-14.70%，120日回撤-21.19%。MA60(274.75)和布林下轨(280.46)构成支撑，止损位280.56距现价仅4.9%。技术面不支持14.26%超配仓位。",
        "atr_pct": 8.33,
        "bollinger_upper": 355.16,
        "bollinger_lower": 280.46,
        "ma20": 317.81,
        "ma60": 274.75,
        "ma60_high": 374.50,
        "rsi14": 48.1,
        "rsi6": 29.9,
        "vol_ratio": 0.94,
        "macd_dif": 9.55,
        "macd_dea": 12.77,
        "macd_hist": -6.44,
        "kdj_k": 50.5,
        "kdj_d": 61.0,
        "kdj_j": 29.6,
        "drawdown_10d_pct": -14.70,
        "drawdown_120d_pct": -21.19,
        "obv_5d_change_pct": -2.97,
        "bias": "偏空"
      },
      "fundamental": {
        "score": 7,
        "note": "营收增长强劲：2025全年营收13.30亿(+40.82% YoY)，受益于AI数据中心建设拉动高速光器件需求。公司为光器件整体解决方案龙头，苏州/新加坡双总部+江西/泰国双基地布局完善。5127名员工，产品覆盖无源光器件+光电先进封装两大板块。但营收增速已从前期更高水平放缓，应付票据+158%和应收款项融资+714%暗示营运资金压力增大。机构研报不可用，无法获取最新目标价和评级信息。"
      },
      "valuation": {
        "score": 2,
        "note": "PE TTM 148.24为光模块三杰中最高（中际91.02/新易盛72.31），估值溢价显著。6/12完成10送4除权后PE仍高达148x，对应除权前约207x。PE处于2年分位数约75-85%（高于历史中位数）。营收增速40%无法支撑148倍PE（PEG≈3.7），估值严重透支。PB/PS分位数因数据源限制无法获取。在板块集体回调中天孚跌幅最深(-7.19% vs 板块均值-3.8%)，反映市场对其高估值的惩罚力度最强。",
        "pe_ttm": 148.24,
        "pe_percentile_2yr": "75-85%",
        "peer_pe_comparison": "中际旭创91.02 / 新易盛72.31",
        "pb_percentile": "数据不可用",
        "ps_percentile": "数据不可用"
      },
      "financials": {
        "score": 6,
        "note": "2025年报：营收13.30亿(+40.82%)，营业成本5.77亿(+30.15%)，成本增速低于营收增速，毛利率趋势向好。但经营活动现金流1.82亿(-37.92% YoY)，主因原材料采购支出和税费支出增加，现金转化率下降。在建工程1.18亿(-41.62%)转固顺利。预付款9663万(+365%)和应付票据2.39亿(+158%)显示扩产积极但资金占用加大。ROE/净利率数据因API不可用缺失。整体财务质量尚可但现金流恶化值得关注。"
      }
    },
    "peer_comparison": {
      "300308_中际旭创": "收盘1220.00(-2.70%) PE=91.02 RSI(14)=56.2 10日回撤-13.90% vsMA20=-1.42%",
      "300502_新易盛": "收盘556.96(-1.60%) PE=72.31 RSI(14)=56.3 10日回撤-8.81% vsMA20=+1.51%",
      "300394_天孚通信": "收盘295.15(-7.19%) PE=148.24 RSI(14)=48.1 10日回撤-14.70% vsMA20=-7.13%",
      "conclusion": "天孚在同板块中跌幅最深、PE最高、短期技术面最弱、回撤幅度最大。板块整体回调但天孚承受的抛压显著大于同行。"
    },
    "summary": "技术面全面偏空（评分3/10）：单日-7.19%放量长阴，跌破MA5/10/20三道均线，MACD死叉，RSI(6)逼近超卖，ATR 8.33%极端波动。基本面尚可（评分7/10）：营收+40.82%高增长，AI光器件需求强劲。但估值极高（评分2/10）：PE 148x为板块最高，PEG≈3.7严重透支，6/12除权后仍处历史高分位。财务质量一般（评分6/10）：营收增长强劲但经营现金流-37.92%恶化，营运资金压力增大。机构研报数据不可用。295.15价位技术面偏空，距离止损位280.56仅4.9%，ATR(14)=24.59意味着1个ATR即可触及止损。当前14.26%仓位突破10%单股上限，技术面不支持此超配仓位。建议维持CIO原裁决（7%）。如坚持14.26%，需接受2周内触及止损280.56（概率>50%基于当前波动率），届时将面临约5%本金损失（占总资产约0.71%）。"
  }
}
